README.rst
setup.py
leetx_parser/__init__.py
leetx_parser/leetx_parser.py
leetx_parser.egg-info/PKG-INFO
leetx_parser.egg-info/SOURCES.txt
leetx_parser.egg-info/dependency_links.txt
leetx_parser.egg-info/requires.txt
leetx_parser.egg-info/top_level.txt
tests/__init__.py
tests/context.py
tests/test_leetx_parser.py