Metadata-Version: 1.1
Name: leetx-parser
Version: 0.2.3
Summary: Find magnet links for TV show episodes
Home-page: https://github.com/evgeny1602/leetx_parser
Author: Evgeny Lobanov
Author-email: evgeny1602@gmail.com
License: UNKNOWN
Platform: UNKNOWN
Classifier: Development Status :: 2 - Pre-Alpha
Classifier: Programming Language :: Python
Classifier: Programming Language :: Python :: 2
Classifier: Programming Language :: Python :: 2.7
Classifier: Programming Language :: Python :: 3
Classifier: Programming Language :: Python :: 3.4
Classifier: Programming Language :: Python :: 3.5
